{
  "Recent": [
    {
      "Name": "exalted",
      "IPI": 314398,
      "PRO": "User"
    },
    {
      "Name": "asdoc",
      "IPI": 314398,
      "PRO": "Admin"
    },
    {
      "Name": "otiyuo",
      "IPI": 314398,
      "PRO": "User"
    },
      {
      "Name": "lkdfgl",
      "IPI": 314398,
      "PRO": "Admin"
    },
    {
      "Name": "alksdhh",
      "IPI": 314398,
      "PRO": "User"
    }
    
  ],
   "Result": [
    {
      "Name": "keras",
      "IPI": 314398,
      "PRO": "User"
    },
    {
      "Name": "asduquette",
      "IPI": 314398,
      "PRO": "Org"
    },
    {
      "Name": "asduquette",
      "IPI": 314398,
      "PRO": "User"
    },
     {
      "Name": "rainbowsoft",
      "IPI": 314398,
      "PRO": "Admin"
    },
    {
      "Name": "zjgzyv",
      "IPI": 314398,
      "PRO": "User"
    }
  ]
}
